cpanlp/__init__.py
cpanlp/calculate.py
cpanlp/cas.py
cpanlp/params.py
cpanlp/stocktrade.py
cpanlp/accounting/__init__.py
cpanlp/accounting/assets/__init__.py
cpanlp/accounting/assets/asset.py
cpanlp/accounting/assets/fixedasset.py
cpanlp/accounting/assets/inventory.py
cpanlp/accounting/assets/investmentproperty.py
cpanlp/accounting/assets/financialassets/__init__.py
cpanlp/accounting/assets/financialassets/bankdeposit.py
cpanlp/accounting/assets/financialassets/financialasset.py
cpanlp/accounting/assets/financialassets/stock.py
cpanlp/accounting/assets/intangibleasset/__init__.py
cpanlp/accounting/assets/intangibleasset/franchise.py
cpanlp/accounting/assets/intangibleasset/goodwill.py
cpanlp/accounting/assets/intangibleasset/intangibleasset.py
cpanlp/accounting/assets/intangibleasset/intellectualproperty.py
cpanlp/accounting/assets/intangibleasset/landuseright.py
cpanlp/accounting/assets/intangibleasset/patent.py
cpanlp/accounting/cashflow/__init__.py
cpanlp/accounting/cashflow/cash_flow_rights.py
cpanlp/accounting/cashflow/cashflow.py
cpanlp/accounting/equities/__init__.py
cpanlp/accounting/equities/equity.py
cpanlp/accounting/equities/ownership_structure.py
cpanlp/accounting/equities/retainedearnings.py
cpanlp/accounting/equities/share.py
cpanlp/accounting/income/__init__.py
cpanlp/accounting/income/non_operating_income.py
cpanlp/accounting/income/revenue.py
cpanlp/accounting/liabilities/__init__.py
cpanlp/accounting/liabilities/financial_liability.py
cpanlp/accounting/liabilities/liability.py
cpanlp/accounting/policy/__init__.py
cpanlp/accounting/policy/accounting_policy_choice.py
cpanlp/accounting/policy/accountingpolicy.py
cpanlp/accounting/policy/dividendpolicy.py
cpanlp/accounting/policy/policy.py
cpanlp/accounting/report/__init__.py
cpanlp/accounting/report/earningsmanagement/__init__.py
cpanlp/accounting/report/earningsmanagement/accounting_manipulation.py
cpanlp/accounting/report/earningsmanagement/earnings_management.py
cpanlp-1.2.75.dist-info/LICENSE
cpanlp-1.2.75.dist-info/METADATA
cpanlp-1.2.75.dist-info/WHEEL
cpanlp-1.2.75.dist-info/top_level.txt
cpanlp-1.2.75.dist-info/RECORD
