Metadata-Version: 2.1
Name: cpanlp
Version: 1.2.75
Summary: Communicate in Business with python
Home-page: https://cpanlp.com
Author: Draco Deng
Author-email: dracodeng6@gmail.com
License: MIT
Keywords: machine language,python,accounting,cpa,audit,intelligent accounting,linguistic turn,linguistic,intelligent audit,natural language processing,machine learning,finance,certified public accountant,big four
Classifier: Development Status :: 5 - Production/Stable
Classifier: Intended Audience :: Developers
Classifier: Intended Audience :: Financial and Insurance Industry
Classifier: License :: OSI Approved :: MIT License
Classifier: Programming Language :: Python :: 3
Classifier: Operating System :: Unix
Classifier: Operating System :: MacOS :: MacOS X
Classifier: Operating System :: Microsoft :: Windows
Classifier: Natural Language :: English
Classifier: Natural Language :: Chinese (Simplified)
Classifier: Topic :: Office/Business :: Financial
Classifier: Topic :: Office/Business :: Financial :: Accounting
Classifier: Topic :: Office/Business :: Financial :: Investment
License-File: LICENSE
